{"target_method": "firstElementSibling", "signature": "Element firstElementSibling()", "gwt_enhancements": {"Given": {"enhanced_by": [{"method_name": "parent()", "relation_type": "Parent Element Access", "confidence": 0.9, "reason": "The method 'firstElementSibling' relies on the parent element to find sibling elements.", "is_external": false}, {"method_name": "childElementsList()", "relation_type": "Child Element List Access", "confidence": 0.8, "reason": "The method 'firstElementSibling' accesses the list of child elements to determine the first sibling element.", "is_external": false}]}, "When": {"enhanced_by": [{"method_name": "indexInList(Element, List<Element>)", "relation_type": "Sibling Index Calculation", "confidence": 0.7, "reason": "The method 'firstElementSibling' calculates the index of the current element in the list of sibling elements.", "is_external": false}]}}}