{"target_method": "variable", "signature": "Variable variable(String)", "direct_enhancements": [{"method_name": "solve(Term)", "relation_type": "Behavioral Similarity", "confidence": 0.85, "reason": "Both methods involve operations on variables, with 'solve' evaluating terms and 'variable' managing variable creation and retrieval.", "is_external": false}, {"method_name": "not(Term)", "relation_type": "Structural Similarity", "confidence": 0.75, "reason": "Both methods involve creating new terms, with 'not' creating a negation term and 'variable' creating a variable term.", "is_external": false}, {"method_name": "and(Term...)", "relation_type": "Structural Similarity", "confidence": 0.75, "reason": "Both methods involve creating new terms, with 'and' creating an AND term and 'variable' creating a variable term.", "is_external": false}, {"method_name": "or(Term...)", "relation_type": "Structural Similarity", "confidence": 0.75, "reason": "Both methods involve creating new terms, with 'or' creating an OR term and 'variable' creating a variable term.", "is_external": false}]}