{"target_method": "loanBorrowHistory", "signature": "String loanBorrowHistory(Map<String, Object>)", "direct_enhancements": [{"method_name": "loanIncome(Map<String, Object>)", "relation_type": "Behavioral Similarity", "confidence": 0.9, "reason": "Both methods retrieve historical data related to loans but focus on different aspects (income vs. borrow history).", "is_external": false}, {"method_name": "loanOngoingOrders(Map<String, Object>)", "relation_type": "Behavioral Similarity", "confidence": 0.85, "reason": "Both methods deal with loan-related orders but focus on different states (history vs. ongoing).", "is_external": false}, {"method_name": "loanRepayHistory(Map<String, Object>)", "relation_type": "Behavioral Similarity", "confidence": 0.8, "reason": "Both methods retrieve historical data but focus on different loan lifecycle stages (borrow vs. repay).", "is_external": false}, {"method_name": "loanAdjustLTVHistory(Map<String, Object>)", "relation_type": "Behavioral Similarity", "confidence": 0.75, "reason": "Both methods retrieve historical data but focus on different aspects of loan management (borrow vs. LTV adjustment).", "is_external": false}, {"method_name": "flexibleLoanBorrowHistory(Map<String, Object>)", "relation_type": "Behavioral Similarity", "confidence": 0.8, "reason": "Both methods retrieve historical data related to loan borrows but differ in loan type (standard vs. flexible).", "is_external": false}], "gwt_enhancements": {"Given": {"enhanced_by": [{"method_name": "initializeLoanParameters(Map<String, Object>)", "relation_type": "State Change Similarity", "confidence": 0.85, "reason": "Both methods require similar initialization of loan parameters.", "is_external": false}]}, "When": {"enhanced_by": [{"method_name": "setupLoanEnvironment(Map<String, Object>)", "relation_type": "Resource Access Similarity", "confidence": 0.75, "reason": "Environment setup is required before retrieving loan borrow history.", "is_external": false}]}, "Then": {"enhanced_by": [{"method_name": "verifyLoanHistory(Map<String, Object>)", "relation_type": "Exception Handling Similarity", "confidence": 0.9, "reason": "Both methods verify loan history and handle similar exceptions.", "is_external": false}]}}}