{"target_method": "equals", "signature": "boolean equals(Object)", "gwt_enhancements": {"When": {"enhanced_by": [{"method_name": "setLeft(String)", "relation_type": "State Dependency", "confidence": 0.9, "reason": "Setting the left value is necessary to ensure the equals method has a valid state to compare.", "is_external": false}, {"method_name": "setRight(String)", "relation_type": "State Dependency", "confidence": 0.9, "reason": "Setting the right value is necessary to ensure the equals method has a valid state to compare.", "is_external": false}]}, "Then": {"enhanced_by": [{"method_name": "isChanged()", "relation_type": "Behavior Similarity", "confidence": 0.8, "reason": "Both methods involve comparing the left and right values, making isChanged a good candidate for asserting the outcome of equals.", "is_external": false}, {"method_name": "hashCode()", "relation_type": "Consistency Check", "confidence": 0.75, "reason": "Ensuring that the hashCode method returns consistent results when equals returns true can help verify the correctness of the equals method.", "is_external": false}]}}}