{"target_method": "toString", "signature": "String toString()", "gwt_enhancements": {"Given": {"enhanced_by": [{"method_name": "addOption(Option)", "relation_type": "State Change Similarity", "confidence": 0.9, "reason": "The toString method relies on the options added to the group, which are managed by the addOption method.", "is_external": false}, {"method_name": "setSelected(Option)", "relation_type": "State Change Similarity", "confidence": 0.7, "reason": "The selected option may influence the string representation, though less directly than the options themselves.", "is_external": false}]}, "When": {"enhanced_by": [{"method_name": "getOptions()", "relation_type": "Resource Access Similarity", "confidence": 0.8, "reason": "The toString method directly uses the result of getOptions to build its string representation.", "is_external": false}, {"method_name": "isSelected()", "relation_type": "State Dependency", "confidence": 0.6, "reason": "The selected state might influence the string representation, though it is not directly used in the toString method.", "is_external": false}]}}}