{"target_method": "elements", "signature": "Elements elements()", "direct_enhancements": [{"method_name": "formData()", "relation_type": "Behavioral Similarity", "confidence": 0.9, "reason": "Both methods involve processing form elements and collecting data from them.", "is_external": false}, {"method_name": "submit()", "relation_type": "Dependency", "confidence": 0.85, "reason": "The submit method relies on the elements method to gather form data before submission.", "is_external": false}, {"method_name": "select(Evaluator)", "relation_type": "Structural Similarity", "confidence": 0.8, "reason": "Both methods involve selecting elements based on certain criteria, with similar control flow and exception handling.", "is_external": false}, {"method_name": "addElement(Element)", "relation_type": "Resource Access Similarity", "confidence": 0.75, "reason": "Both methods manipulate the list of form elements, with addElement adding new elements that elements() might later process.", "is_external": false}, {"method_name": "removeAttr(String)", "relation_type": "Exception Handling Similarity", "confidence": 0.7, "reason": "Both methods handle potential exceptions related to element manipulation and attribute removal.", "is_external": false}, {"method_name": "text()", "relation_type": "Behavioral Similarity", "confidence": 0.65, "reason": "Both methods involve extracting or manipulating text content from elements, though in different contexts.", "is_external": false}, {"method_name": "html()", "relation_type": "Substitutability", "confidence": 0.6, "reason": "Both methods generate HTML content, though elements() focuses on form elements and html() on the entire document.", "is_external": false}, {"method_name": "clone()", "relation_type": "Structural Similarity", "confidence": 0.55, "reason": "Both methods involve creating copies of elements, though clone() is more general and elements() is specific to form elements.", "is_external": false}, {"method_name": "createFromEncoded(String)", "relation_type": "Substitutability", "confidence": 0.5, "reason": "Both methods involve creating elements from encoded data, though createFromEncoded is more specific to text nodes.", "is_external": true, "class_name": "TextNode"}]}