{"target_method": "getDataLength", "signature": "char getDataLength()", "direct_enhancements": [{"method_name": "encode()", "relation_type": "Structural Similarity", "confidence": 0.9, "reason": "Both methods involve operations related to the realm attribute's length and encoding.", "is_external": false}, {"method_name": "decodeAttributeBody(byte[], char, char)", "relation_type": "Behavioral Similarity", "confidence": 0.85, "reason": "Both methods process the realm attribute's data and length.", "is_external": false}, {"method_name": "equals(Object)", "relation_type": "Exception Handling Similarity", "confidence": 0.75, "reason": "Both methods handle comparisons and potential exceptions related to attribute length.", "is_external": false}], "gwt_enhancements": {"Given": {"enhanced_by": [{"method_name": "setRealm(byte[])", "relation_type": "State Change Similarity", "confidence": 0.8, "reason": "Setting the realm attribute is necessary to test the length calculation.", "is_external": false}]}, "When": {"enhanced_by": [{"method_name": "encode()", "relation_type": "Resource Access Similarity", "confidence": 0.7, "reason": "Encoding the attribute requires the length to be calculated.", "is_external": false}]}, "Then": {"enhanced_by": [{"method_name": "equals(Object)", "relation_type": "Exception Handling Similarity", "confidence": 0.85, "reason": "Comparing attributes involves verifying the length and data.", "is_external": false}]}}}