{"original": {}, "apt": {"org.apache.commons.cli.Option[boolean]addValue(String)": [{"Instruction Coverage": 1.0}, {"Branch Coverage": -1.0}, {"Line Coverage": 1.0}], "org.apache.commons.cli.Option[boolean]equals(Object)": [{"Instruction Coverage": 1.0}, {"Branch Coverage": 0.875}, {"Line Coverage": 1.0}], "org.apache.commons.cli.Option[String]getValue(String)": [{"Instruction Coverage": 1.0}, {"Branch Coverage": 1.0}, {"Line Coverage": 1.0}], "org.apache.commons.cli.Option[int]hashCode()": [{"Instruction Coverage": 1.0}, {"Branch Coverage": -1.0}, {"Line Coverage": 1.0}], "org.apache.commons.cli.Option[void]setType(Object)": [{"Instruction Coverage": 1.0}, {"Branch Coverage": -1.0}, {"Line Coverage": 1.0}], "org.apache.commons.cli.OptionGroup[OptionGroup]addOption(Option)": [{"Instruction Coverage": 1.0}, {"Branch Coverage": -1.0}, {"Line Coverage": 1.0}], "org.apache.commons.cli.OptionGroup[Collection<String>]getNames()": [{"Instruction Coverage": 1.0}, {"Branch Coverage": -1.0}, {"Line Coverage": 1.0}], "org.apache.commons.cli.OptionGroup[Collection<Option>]getOptions()": [{"Instruction Coverage": 1.0}, {"Branch Coverage": -1.0}, {"Line Coverage": 1.0}], "org.apache.commons.cli.OptionGroup[void]setSelected(Option)": [{"Instruction Coverage": 1.0}, {"Branch Coverage": 1.0}, {"Line Coverage": 1.0}], "org.apache.commons.cli.OptionGroup[String]toString()": [{"Instruction Coverage": 1.0}, {"Branch Coverage": 0.875}, {"Line Coverage": 1.0}], "org.apache.commons.cli.ParseException[ParseException]wrap(Throwable)": [{"Instruction Coverage": 1.0}, {"Branch Coverage": 1.0}, {"Line Coverage": 1.0}], "org.apache.commons.cli.TypeHandler[Number]createNumber(String)": [{"Instruction Coverage": 1.0}, {"Branch Coverage": -1.0}, {"Line Coverage": 1.0}], "org.apache.commons.cli.TypeHandler[Object]createObject(String)": [{"Instruction Coverage": 1.0}, {"Branch Coverage": -1.0}, {"Line Coverage": 1.0}], "org.apache.commons.cli.TypeHandler[T]createValue(String,Class<T>)": [{"Instruction Coverage": 1.0}, {"Branch Coverage": -1.0}, {"Line Coverage": 1.0}], "org.apache.commons.cli.TypeHandler[Converter<T, ?>]getConverter(Class<T>)": [{"Instruction Coverage": 1.0}, {"Branch Coverage": -1.0}, {"Line Coverage": 1.0}], "org.apache.commons.cli.Options[Options]addOption(Option)": [{"Instruction Coverage": 0.8095238095238095}, {"Branch Coverage": 0.8333333333333334}, {"Line Coverage": 0.8888888888888888}], "org.apache.commons.cli.Options[Options]addOptionGroup(OptionGroup)": [{"Instruction Coverage": 1.0}, {"Branch Coverage": 1.0}, {"Line Coverage": 1.0}], "org.apache.commons.cli.Options[Options]addOptions(Options)": [{"Instruction Coverage": 1.0}, {"Branch Coverage": 1.0}, {"Line Coverage": 1.0}], "org.apache.commons.cli.Options[Options]addRequiredOption(String,String,boolean,String)": [{"Instruction Coverage": 1.0}, {"Branch Coverage": -1.0}, {"Line Coverage": 1.0}], "org.apache.commons.cli.Options[List<String>]getMatchingOptions(String)": [{"Instruction Coverage": 1.0}, {"Branch Coverage": 1.0}, {"Line Coverage": 1.0}], "org.apache.commons.cli.Options[Option]getOption(String)": [{"Instruction Coverage": 1.0}, {"Branch Coverage": 1.0}, {"Line Coverage": 1.0}], "org.apache.commons.cli.Options[boolean]hasOption(String)": [{"Instruction Coverage": 1.0}, {"Branch Coverage": 1.0}, {"Line Coverage": 1.0}], "org.apache.commons.cli.Options[boolean]hasShortOption(String)": [{"Instruction Coverage": 1.0}, {"Branch Coverage": -1.0}, {"Line Coverage": 1.0}], "org.apache.commons.cli.PatternOptionBuilder[Object]getValueClass(char)": [{"Instruction Coverage": 1.0}, {"Branch Coverage": -1.0}, {"Line Coverage": 1.0}], "org.apache.commons.cli.PatternOptionBuilder[Class<?>]getValueType(char)": [{"Instruction Coverage": 1.0}, {"Branch Coverage": 1.0}, {"Line Coverage": 1.0}], "org.apache.commons.cli.PatternOptionBuilder[Options]parsePattern(String)": [{"Instruction Coverage": 1.0}, {"Branch Coverage": 0.9285714285714286}, {"Line Coverage": 1.0}], "org.apache.commons.cli.DeprecatedAttributes[String]toString()": [{"Instruction Coverage": 1.0}, {"Branch Coverage": 1.0}, {"Line Coverage": 1.0}], "org.apache.commons.cli.OptionBuilder[Option]create()": [{"Instruction Coverage": 1.0}, {"Branch Coverage": 1.0}, {"Line Coverage": 1.0}], "org.apache.commons.cli.OptionBuilder[OptionBuilder]hasArgs()": [{"Instruction Coverage": 1.0}, {"Branch Coverage": -1.0}, {"Line Coverage": 1.0}], "org.apache.commons.cli.OptionBuilder[OptionBuilder]hasOptionalArg()": [{"Instruction Coverage": 1.0}, {"Branch Coverage": -1.0}, {"Line Coverage": 1.0}], "org.apache.commons.cli.OptionBuilder[OptionBuilder]withArgName(String)": [{"Instruction Coverage": 1.0}, {"Branch Coverage": -1.0}, {"Line Coverage": 1.0}], "org.apache.commons.cli.OptionBuilder[OptionBuilder]withDescription(String)": [{"Instruction Coverage": 1.0}, {"Branch Coverage": -1.0}, {"Line Coverage": 1.0}], "org.apache.commons.cli.OptionBuilder[OptionBuilder]withLongOpt(String)": [{"Instruction Coverage": 1.0}, {"Branch Coverage": -1.0}, {"Line Coverage": 1.0}], "org.apache.commons.cli.HelpFormatter[String]getDescription(Option)": [{"Instruction Coverage": 1.0}, {"Branch Coverage": 1.0}, {"Line Coverage": 1.0}], "org.apache.commons.cli.HelpFormatter[void]printUsage(PrintWriter,int,String)": [{"Instruction Coverage": 1.0}, {"Branch Coverage": 0.0}, {"Line Coverage": 1.0}]}}