{"target_method": "matchesAny", "signature": "boolean matchesAny(Iterator<E>, Predicate<? super E>)", "gwt_enhancements": {"Given": {"enhanced_by": [{"method_name": "filteredIterator(Iterator<? extends E>, Predicate<? super E>)", "relation_type": "Input Pattern Similarity", "confidence": 0.9, "reason": "Both methods involve filtering elements based on a predicate.", "is_external": false}, {"method_name": "find(Iterator<E>, Predicate<? super E>)", "relation_type": "Input Pattern Similarity", "confidence": 0.85, "reason": "Both methods involve searching for elements that match a predicate.", "is_external": false}]}, "Then": {"enhanced_by": [{"method_name": "contains(Iterator<E>, Object)", "relation_type": "Output Behavior Similarity", "confidence": 0.8, "reason": "Both methods return a boolean indicating the presence of an element that matches a condition.", "is_external": false}, {"method_name": "indexOf(Iterator<E>, Predicate<? super E>)", "relation_type": "Output Behavior Similarity", "confidence": 0.75, "reason": "Both methods involve finding the presence of an element that matches a predicate and return a related result.", "is_external": false}]}}}