{"target_method": "pushbackIterator", "signature": "PushbackIterator<E> pushbackIterator(Iterator<? extends E>)", "gwt_enhancements": {"Given": {"enhanced_by": [{"method_name": "PushbackIterator(Iterator<? extends E>)", "relation_type": "Object Initialization Similarity", "confidence": 0.9, "reason": "Both methods involve initializing a PushbackIterator with an Iterator.", "is_external": false}, {"method_name": "Objects.requireNonNull(Object, String)", "relation_type": "Input Validation Similarity", "confidence": 0.85, "reason": "Both methods validate the input Iterator for null.", "is_external": true}]}, "Then": {"enhanced_by": [{"method_name": "hasNext()", "relation_type": "State Check Similarity", "confidence": 0.8, "reason": "Both methods involve checking the state of the Iterator and the pushback queue.", "is_external": false}, {"method_name": "next()", "relation_type": "Data Retrieval Similarity", "confidence": 0.85, "reason": "Both methods involve retrieving data from the Iterator or the pushback queue.", "is_external": false}]}}}