{"target_method": "putAll", "signature": "void putAll(Map<? extends K, ? extends V>)", "gwt_enhancements": {"Given": {"enhanced_by": [{"method_name": "transformMap(Map<? extends K, ? extends V>)", "relation_type": "State Change Similarity", "confidence": 0.9, "reason": "Both methods involve transforming a map before adding it to the decorated map.", "is_external": false}, {"method_name": "transformedMap(Map<K, V>, Transformer<? super K, ? extends K>, Transformer<? super V, ? extends V>)", "relation_type": "Object Initialization Similarity", "confidence": 0.85, "reason": "The transformedMap method initializes a map with transformations, similar to the setup needed for putAll.", "is_external": false}]}, "Then": {"enhanced_by": [{"method_name": "put(K, V)", "relation_type": "Behavior Similarity", "confidence": 0.8, "reason": "The put method adds a single key-value pair to the map, which can be used to verify the behavior of putAll by checking multiple entries.", "is_external": false}, {"method_name": "LinkedMap(Map<? extends K, ? extends V>)", "relation_type": "Output Similarity", "confidence": 0.75, "reason": "The LinkedMap constructor initializes a map, which can be used to verify the output of putAll by comparing the resulting maps.", "is_external": true}]}}}