{"target_method": "tradeFlow", "signature": "String tradeFlow(Map<String, Object>)", "gwt_enhancements": {"When": {"enhanced_by": [{"method_name": "exchangeInfo(Map<String, Object>)", "relation_type": "Prerequisite Data Fetching", "confidence": 0.75, "reason": "Fetching exchange information can provide context for the trade flow, ensuring the parameters are valid.", "is_external": false}, {"method_name": "assetQuantityPrecision(Map<String, Object>)", "relation_type": "Prerequisite Data Fetching", "confidence": 0.7, "reason": "Knowing the asset quantity precision can help in validating the trade flow parameters.", "is_external": false}]}, "Then": {"enhanced_by": [{"method_name": "orderStatus(Map<String, Object>)", "relation_type": "Post-Condition Verification", "confidence": 0.8, "reason": "Verifying the order status after the trade flow can ensure the trade was processed correctly.", "is_external": false}, {"method_name": "quoteInquiry(Map<String, Object>)", "relation_type": "Behavior Similarity", "confidence": 0.7, "reason": "Both methods involve sending requests related to asset conversion, which can inform assertions about the trade flow.", "is_external": false}]}}}