{"target_method": "getSignature", "signature": "String getSignature(String)", "gwt_enhancements": {"When": {"enhanced_by": [{"method_name": "ParameterChecker.checkParameterType(String,Class,String)", "relation_type": "Precondition Check", "confidence": 0.9, "reason": "ParameterChecker.checkParameterType is invoked in the constructor to ensure the apiSecret is of the correct type before any signature generation occurs.", "is_external": true}]}, "Then": {"enhanced_by": [{"method_name": "Hex.encodeHexString(byte[])", "relation_type": "Output Transformation", "confidence": 0.85, "reason": "The getSignature method uses Hex.encodeHexString to convert the byte array to a hexadecimal string, which is the final output format.", "is_external": true}]}}}