{"target_method": "getIpRestriction", "signature": "String getIpRestriction(Map<String, Object>)", "gwt_enhancements": {"When": {"enhanced_by": [{"method_name": "setupEnvironment()", "relation_type": "Resource Access Similarity", "confidence": 0.7, "reason": "Environment setup is required before accessing IP restriction details.", "is_external": false}, {"method_name": "validateSubAccountApiKey(String)", "relation_type": "Parameter Validation", "confidence": 0.85, "reason": "Validation of subAccountApiKey is necessary to ensure the key is valid before fetching IP restrictions.", "is_external": false}]}, "Then": {"enhanced_by": [{"method_name": "verifyIpRestrictionResponse(String)", "relation_type": "Response Validation", "confidence": 0.9, "reason": "The response from getIpRestriction should be validated to ensure it contains the expected IP restriction details.", "is_external": false}, {"method_name": "compareIpRestrictions(String, String)", "relation_type": "Behavioral Similarity", "confidence": 0.8, "reason": "Comparing the IP restrictions with a previously known state can help verify if the restrictions have changed as expected.", "is_external": false}]}}}