{"target_method": "slug", "signature": "String slug(List<String>, String)", "gwt_enhancements": {"Given": {"enhanced_by": [{"method_name": "lorem().words(int)", "relation_type": "Input Data Similarity", "confidence": 0.9, "reason": "The slug method uses words from the lorem provider, which can be directly reused for setting up test cases.", "is_external": false}, {"method_name": "stripAccents(String)", "relation_type": "Data Transformation Similarity", "confidence": 0.7, "reason": "Both methods involve string manipulation and normalization, which can be useful for preparing test inputs.", "is_external": false}]}, "When": {"enhanced_by": [{"method_name": "url(boolean, boolean, boolean, boolean, boolean, boolean)", "relation_type": "State Dependency", "confidence": 0.8, "reason": "The url method constructs URLs that might include slugs, indicating a potential state dependency that should be considered in test setup.", "is_external": false}, {"method_name": "domainName()", "relation_type": "Resource Access Similarity", "confidence": 0.6, "reason": "The domainName method generates domain names that could be part of a URL, suggesting a potential dependency on the state generated by domainName.", "is_external": false}]}}}