{"target_method": "createLineDouble_", "signature": "int createLineDouble_(FlatBufferBuilder, double, double, double, double)", "gwt_enhancements": {"When": {"enhanced_by": [{"method_name": "FlatBufferBuilder.prep(int, int)", "relation_type": "Preparation Dependency", "confidence": 0.9, "reason": "The createLineDouble_ method relies on the FlatBufferBuilder being prepared with the correct size before adding data.", "is_external": true}, {"method_name": "FlatBufferBuilder.putDouble(double)", "relation_type": "Data Insertion Dependency", "confidence": 0.85, "reason": "The createLineDouble_ method inserts double values into the FlatBufferBuilder, which is dependent on the putDouble method.", "is_external": true}]}, "Then": {"enhanced_by": [{"method_name": "FlatBufferBuilder.offset()", "relation_type": "Result Verification", "confidence": 0.9, "reason": "The createLineDouble_ method returns the offset from the FlatBufferBuilder, which can be verified using the offset method.", "is_external": true}, {"method_name": "LineDouble_.minX()", "relation_type": "Data Retrieval Similarity", "confidence": 0.8, "reason": "The createLineDouble_ method inserts minX, which can be verified by retrieving it using the minX method.", "is_external": false}, {"method_name": "LineDouble_.minY()", "relation_type": "Data Retrieval Similarity", "confidence": 0.8, "reason": "The createLineDouble_ method inserts minY, which can be verified by retrieving it using the minY method.", "is_external": false}, {"method_name": "LineDouble_.maxX()", "relation_type": "Data Retrieval Similarity", "confidence": 0.8, "reason": "The createLineDouble_ method inserts maxX, which can be verified by retrieving it using the maxX method.", "is_external": false}, {"method_name": "LineDouble_.maxY()", "relation_type": "Data Retrieval Similarity", "confidence": 0.8, "reason": "The createLineDouble_ method inserts maxY, which can be verified by retrieving it using the maxY method.", "is_external": false}]}}}