{"target_method": "transformedBag", "signature": "Bag<E> transformedBag(Bag<E>, Transformer<? super E, ? extends E>)", "direct_enhancements": [{"method_name": "transformingBag(Bag<E>, Transformer<? super E, ? extends E>)", "relation_type": "Behavioral Similarity", "confidence": 0.9, "reason": "Both methods create transformed bags but differ in how they handle existing elements.", "is_external": false}, {"method_name": "transform(E)", "relation_type": "Structural Similarity", "confidence": 0.85, "reason": "Both methods involve transforming elements, sharing similar control flows and exception handling.", "is_external": false}, {"method_name": "uniqueSet()", "relation_type": "Resource Access Similarity", "confidence": 0.75, "reason": "Both methods manipulate the bag's elements and involve set operations.", "is_external": false}, {"method_name": "TransformedSet.transformingSet(Set<E>, Transformer<? super E, ? extends E>)", "relation_type": "Substitutability", "confidence": 0.8, "reason": "Both methods transform collections using a transformer, but operate on different types (Bag vs Set).", "is_external": true, "class_name": "TransformedSet"}], "gwt_enhancements": {"Given": {"enhanced_by": [{"method_name": "initializeTransformer()", "relation_type": "State Change Similarity", "confidence": 0.8, "reason": "Both methods require a transformer to be initialized before transformation operations.", "is_external": false}]}, "When": {"enhanced_by": [{"method_name": "setupBag()", "relation_type": "Resource Access Similarity", "confidence": 0.7, "reason": "Setting up the bag is required before transforming its elements.", "is_external": false}]}, "Then": {"enhanced_by": [{"method_name": "verifyTransformation()", "relation_type": "Exception Handling Similarity", "confidence": 0.85, "reason": "Both methods involve verifying the transformation of elements and handling similar exceptions.", "is_external": false}]}}}