{"SinglePortUdpHarvester": [{"method_name": "SinglePortUdpHarvester(TransportAddress)", "file_path": "src/test/java/org/ice4j/ice/harvest/SinglePortUdpHarvesterTest.java", "testclass_name": "SinglePortUdpHarvesterTest", "testcase_name": "testRebindWithoutCloseThrows"}, {"method_name": "SinglePortUdpHarvester(TransportAddress)", "file_path": "src/test/java/org/ice4j/ice/harvest/SinglePortUdpHarvesterTest.java", "testclass_name": "SinglePortUdpHarvesterTest", "testcase_name": "testRebindWithClose"}, {"method_name": "SinglePortUdpHarvester(TransportAddress)", "file_path": "src/test/java/org/ice4j/ice/harvest/SinglePortUdpHarvesterTest.java", "testclass_name": "SinglePortUdpHarvesterTest", "testcase_name": "testBindWithPortZero"}], "RoleConflictResolutionTest": [{"method_name": "testRecoveryFromRoleConflict(boolean)", "file_path": "src/test/java/org/ice4j/ice/RoleConflictResolutionTest.java", "testclass_name": "RoleConflictResolutionTest", "testcase_name": "testRecoveryFromBothControlledConflict"}, {"method_name": "testRecoveryFromRoleConflict(boolean)", "file_path": "src/test/java/org/ice4j/ice/RoleConflictResolutionTest.java", "testclass_name": "RoleConflictResolutionTest", "testcase_name": "testRecoveryFromBothControllingConflict"}], "XorOnlyAttribute": [{"method_name": "decodeAttributeBody(byte[],char,char)", "file_path": "src/test/java/org/ice4j/attribute/XorOnlyTest.java", "testclass_name": "XorOnlyTest", "testcase_name": "testDecodeAttributeBody"}, {"method_name": "encode()", "file_path": "src/test/java/org/ice4j/attribute/XorOnlyTest.java", "testclass_name": "XorOnlyTest", "testcase_name": "testEncode"}, {"method_name": "equals(Object)", "file_path": "src/test/java/org/ice4j/attribute/XorOnlyTest.java", "testclass_name": "XorOnlyTest", "testcase_name": "testEquals"}, {"method_name": "getDataLength()", "file_path": "src/test/java/org/ice4j/attribute/XorOnlyTest.java", "testclass_name": "XorOnlyTest", "testcase_name": "testGetDataLength"}, {"method_name": "getName()", "file_path": "src/test/java/org/ice4j/attribute/XorOnlyTest.java", "testclass_name": "XorOnlyTest", "testcase_name": "testGetName"}], "OptionalAttribute": [{"method_name": "decodeAttributeBody(byte[],char,char)", "file_path": "src/test/java/org/ice4j/attribute/OptionalAttributeAttributeTest.java", "testclass_name": "OptionalAttributeAttributeTest", "testcase_name": "testDecodeAttributeBody"}, {"method_name": "encode()", "file_path": "src/test/java/org/ice4j/attribute/OptionalAttributeAttributeTest.java", "testclass_name": "OptionalAttributeAttributeTest", "testcase_name": "testEncode"}, {"method_name": "equals(Object)", "file_path": "src/test/java/org/ice4j/attribute/OptionalAttributeAttributeTest.java", "testclass_name": "OptionalAttributeAttributeTest", "testcase_name": "testEquals"}, {"method_name": "getDataLength()", "file_path": "src/test/java/org/ice4j/attribute/OptionalAttributeAttributeTest.java", "testclass_name": "OptionalAttributeAttributeTest", "testcase_name": "testGetDataLength"}], "SoftwareAttribute": [{"method_name": "decodeAttributeBody(byte[],char,char)", "file_path": "src/test/java/org/ice4j/attribute/SoftwareAttributeTest.java", "testclass_name": "SoftwareAttributeTest", "testcase_name": "testDecodeAttributeBody"}, {"method_name": "encode()", "file_path": "src/test/java/org/ice4j/attribute/SoftwareAttributeTest.java", "testclass_name": "SoftwareAttributeTest", "testcase_name": "testEncode"}, {"method_name": "equals(Object)", "file_path": "src/test/java/org/ice4j/attribute/SoftwareAttributeTest.java", "testclass_name": "SoftwareAttributeTest", "testcase_name": "testEquals"}, {"method_name": "getDataLength()", "file_path": "src/test/java/org/ice4j/attribute/SoftwareAttributeTest.java", "testclass_name": "SoftwareAttributeTest", "testcase_name": "testGetDataLength"}, {"method_name": "getName()", "file_path": "src/test/java/org/ice4j/attribute/SoftwareAttributeTest.java", "testclass_name": "SoftwareAttributeTest", "testcase_name": "testGetName"}, {"method_name": "setSoftware(byte[])", "file_path": "src/test/java/org/ice4j/attribute/SoftwareAttributeTest.java", "testclass_name": "SoftwareAttributeTest", "testcase_name": "testSetGetSoftware"}, {"method_name": "getSoftware()", "file_path": "src/test/java/org/ice4j/attribute/SoftwareAttributeTest.java", "testclass_name": "SoftwareAttributeTest", "testcase_name": "testSetGetSoftware"}], "UsernameAttribute": [{"method_name": "decodeAttributeBody(byte[],char,char)", "file_path": "src/test/java/org/ice4j/attribute/UsernameAttributeTest.java", "testclass_name": "UsernameAttributeTest", "testcase_name": "testDecodeAttributeBody"}, {"method_name": "encode()", "file_path": "src/test/java/org/ice4j/attribute/UsernameAttributeTest.java", "testclass_name": "UsernameAttributeTest", "testcase_name": "testEncode"}, {"method_name": "equals(Object)", "file_path": "src/test/java/org/ice4j/attribute/UsernameAttributeTest.java", "testclass_name": "UsernameAttributeTest", "testcase_name": "testEquals"}, {"method_name": "getDataLength()", "file_path": "src/test/java/org/ice4j/attribute/UsernameAttributeTest.java", "testclass_name": "UsernameAttributeTest", "testcase_name": "testGetDataLength"}, {"method_name": "getName()", "file_path": "src/test/java/org/ice4j/attribute/UsernameAttributeTest.java", "testclass_name": "UsernameAttributeTest", "testcase_name": "testGetName"}, {"method_name": "setUsername(byte[])", "file_path": "src/test/java/org/ice4j/attribute/UsernameAttributeTest.java", "testclass_name": "UsernameAttributeTest", "testcase_name": "testSetGetUsername"}, {"method_name": "getUsername()", "file_path": "src/test/java/org/ice4j/attribute/UsernameAttributeTest.java", "testclass_name": "UsernameAttributeTest", "testcase_name": "testSetGetUsername"}], "RealmAttribute": [{"method_name": "decodeAttributeBody(byte[],char,char)", "file_path": "src/test/java/org/ice4j/attribute/RealmAttributeTest.java", "testclass_name": "RealmAttributeTest", "testcase_name": "testDecodeAttributeBody"}, {"method_name": "encode()", "file_path": "src/test/java/org/ice4j/attribute/RealmAttributeTest.java", "testclass_name": "RealmAttributeTest", "testcase_name": "testEncode"}, {"method_name": "equals(Object)", "file_path": "src/test/java/org/ice4j/attribute/RealmAttributeTest.java", "testclass_name": "RealmAttributeTest", "testcase_name": "testEquals"}, {"method_name": "getDataLength()", "file_path": "src/test/java/org/ice4j/attribute/RealmAttributeTest.java", "testclass_name": "RealmAttributeTest", "testcase_name": "testGetDataLength"}, {"method_name": "getName()", "file_path": "src/test/java/org/ice4j/attribute/RealmAttributeTest.java", "testclass_name": "RealmAttributeTest", "testcase_name": "testGetName"}, {"method_name": "setRealm(byte[])", "file_path": "src/test/java/org/ice4j/attribute/RealmAttributeTest.java", "testclass_name": "RealmAttributeTest", "testcase_name": "testSetGetRealm"}, {"method_name": "getRealm()", "file_path": "src/test/java/org/ice4j/attribute/RealmAttributeTest.java", "testclass_name": "RealmAttributeTest", "testcase_name": "testSetGetRealm"}], "NonceAttribute": [{"method_name": "decodeAttributeBody(byte[],char,char)", "file_path": "src/test/java/org/ice4j/attribute/NonceAttributeTest.java", "testclass_name": "NonceAttributeTest", "testcase_name": "testDecodeAttributeBody"}, {"method_name": "encode()", "file_path": "src/test/java/org/ice4j/attribute/NonceAttributeTest.java", "testclass_name": "NonceAttributeTest", "testcase_name": "testEncode"}, {"method_name": "equals(Object)", "file_path": "src/test/java/org/ice4j/attribute/NonceAttributeTest.java", "testclass_name": "NonceAttributeTest", "testcase_name": "testEquals"}, {"method_name": "getDataLength()", "file_path": "src/test/java/org/ice4j/attribute/NonceAttributeTest.java", "testclass_name": "NonceAttributeTest", "testcase_name": "testGetDataLength"}, {"method_name": "getName()", "file_path": "src/test/java/org/ice4j/attribute/NonceAttributeTest.java", "testclass_name": "NonceAttributeTest", "testcase_name": "testGetName"}, {"method_name": "setNonce(byte[])", "file_path": "src/test/java/org/ice4j/attribute/NonceAttributeTest.java", "testclass_name": "NonceAttributeTest", "testcase_name": "testSetGetNonce"}, {"method_name": "getNonce()", "file_path": "src/test/java/org/ice4j/attribute/NonceAttributeTest.java", "testclass_name": "NonceAttributeTest", "testcase_name": "testSetGetNonce"}], "ChangeRequestAttribute": [{"method_name": "decodeAttributeBody(byte[],char,char)", "file_path": "src/test/java/org/ice4j/attribute/ChangeRequestAttributeTest.java", "testclass_name": "ChangeRequestAttributeTest", "testcase_name": "testDecodeAttributeBody"}, {"method_name": "encode()", "file_path": "src/test/java/org/ice4j/attribute/ChangeRequestAttributeTest.java", "testclass_name": "ChangeRequestAttributeTest", "testcase_name": "testEncode"}, {"method_name": "equals(Object)", "file_path": "src/test/java/org/ice4j/attribute/ChangeRequestAttributeTest.java", "testclass_name": "ChangeRequestAttributeTest", "testcase_name": "testEquals"}, {"method_name": "getDataLength()", "file_path": "src/test/java/org/ice4j/attribute/ChangeRequestAttributeTest.java", "testclass_name": "ChangeRequestAttributeTest", "testcase_name": "testGetDataLength"}, {"method_name": "getName()", "file_path": "src/test/java/org/ice4j/attribute/ChangeRequestAttributeTest.java", "testclass_name": "ChangeRequestAttributeTest", "testcase_name": "testGetName"}, {"method_name": "getAttributeType()", "file_path": "src/test/java/org/ice4j/attribute/ChangeRequestAttributeTest.java", "testclass_name": "ChangeRequestAttributeTest", "testcase_name": "testChangeRequestAttribute"}], "ConnectionIdAttribute": [{"method_name": "decodeAttributeBody(byte[],char,char)", "file_path": "src/test/java/org/ice4j/attribute/ConnectionIdAttributeTest.java", "testclass_name": "ConnectionIdAttributeTest", "testcase_name": "testDecodeAttributeBody"}, {"method_name": "encode()", "file_path": "src/test/java/org/ice4j/attribute/ConnectionIdAttributeTest.java", "testclass_name": "ConnectionIdAttributeTest", "testcase_name": "testEncode"}, {"method_name": "equals(Object)", "file_path": "src/test/java/org/ice4j/attribute/ConnectionIdAttributeTest.java", "testclass_name": "ConnectionIdAttributeTest", "testcase_name": "testEqualsObject"}, {"method_name": "getDataLength()", "file_path": "src/test/java/org/ice4j/attribute/ConnectionIdAttributeTest.java", "testclass_name": "ConnectionIdAttributeTest", "testcase_name": "testGetDataLength"}, {"method_name": "getName()", "file_path": "src/test/java/org/ice4j/attribute/ConnectionIdAttributeTest.java", "testclass_name": "ConnectionIdAttributeTest", "testcase_name": "testGetName"}, {"method_name": "getConnectionIdValue()", "file_path": "src/test/java/org/ice4j/attribute/ConnectionIdAttributeTest.java", "testclass_name": "ConnectionIdAttributeTest", "testcase_name": "testGetConnectionIdValue"}], "ErrorCodeAttribute": [{"method_name": "decodeAttributeBody(byte[],char,char)", "file_path": "src/test/java/org/ice4j/attribute/ErrorCodeAttributeTest.java", "testclass_name": "ErrorCodeAttributeTest", "testcase_name": "testDecodeAttributeBody"}, {"method_name": "encode()", "file_path": "src/test/java/org/ice4j/attribute/ErrorCodeAttributeTest.java", "testclass_name": "ErrorCodeAttributeTest", "testcase_name": "testEncode"}, {"method_name": "equals(Object)", "file_path": "src/test/java/org/ice4j/attribute/ErrorCodeAttributeTest.java", "testclass_name": "ErrorCodeAttributeTest", "testcase_name": "testEquals"}, {"method_name": "getDataLength()", "file_path": "src/test/java/org/ice4j/attribute/ErrorCodeAttributeTest.java", "testclass_name": "ErrorCodeAttributeTest", "testcase_name": "testGetDataLength"}, {"method_name": "getName()", "file_path": "src/test/java/org/ice4j/attribute/ErrorCodeAttributeTest.java", "testclass_name": "ErrorCodeAttributeTest", "testcase_name": "testGetName"}, {"method_name": "getAttributeType()", "file_path": "src/test/java/org/ice4j/attribute/ErrorCodeAttributeTest.java", "testclass_name": "ErrorCodeAttributeTest", "testcase_name": "testErrorCodeAttribute"}, {"method_name": "getErrorCode()", "file_path": "src/test/java/org/ice4j/attribute/ErrorCodeAttributeTest.java", "testclass_name": "ErrorCodeAttributeTest", "testcase_name": "testGetErrorCode"}, {"method_name": "setErrorCode(char)", "file_path": "src/test/java/org/ice4j/attribute/ErrorCodeAttributeTest.java", "testclass_name": "ErrorCodeAttributeTest", "testcase_name": "testSetErrorCode"}], "RequestedAddressFamilyAttribute": [{"method_name": "decodeAttributeBody(byte[],char,char)", "file_path": "src/test/java/org/ice4j/attribute/RequestedAddressFamilyAttributeTest.java", "testclass_name": "RequestedAddressFamilyAttributeTest", "testcase_name": "testDecodeAttributeBodyV4"}, {"method_name": "decodeAttributeBody(byte[],char,char)", "file_path": "src/test/java/org/ice4j/attribute/RequestedAddressFamilyAttributeTest.java", "testclass_name": "RequestedAddressFamilyAttributeTest", "testcase_name": "testDecodeAttributeBodyV6"}, {"method_name": "encode()", "file_path": "src/test/java/org/ice4j/attribute/RequestedAddressFamilyAttributeTest.java", "testclass_name": "RequestedAddressFamilyAttributeTest", "testcase_name": "testEncodeV4"}, {"method_name": "encode()", "file_path": "src/test/java/org/ice4j/attribute/RequestedAddressFamilyAttributeTest.java", "testclass_name": "RequestedAddressFamilyAttributeTest", "testcase_name": "testEncodeV6"}, {"method_name": "equals(Object)", "file_path": "src/test/java/org/ice4j/attribute/RequestedAddressFamilyAttributeTest.java", "testclass_name": "RequestedAddressFamilyAttributeTest", "testcase_name": "testEqualsObject"}, {"method_name": "getDataLength()", "file_path": "src/test/java/org/ice4j/attribute/RequestedAddressFamilyAttributeTest.java", "testclass_name": "RequestedAddressFamilyAttributeTest", "testcase_name": "testGetDataLength"}, {"method_name": "getName()", "file_path": "src/test/java/org/ice4j/attribute/RequestedAddressFamilyAttributeTest.java", "testclass_name": "RequestedAddressFamilyAttributeTest", "testcase_name": "testGetName"}, {"method_name": "getFamily()", "file_path": "src/test/java/org/ice4j/attribute/RequestedAddressFamilyAttributeTest.java", "testclass_name": "RequestedAddressFamilyAttributeTest", "testcase_name": "testGetFamily"}], "AddressAttribute": [{"method_name": "decodeAttributeBody(byte[],char,char)", "file_path": "src/test/java/org/ice4j/attribute/AddressAttributeTest.java", "testclass_name": "AddressAttributeTest", "testcase_name": "testDecodeAttributeBody"}, {"method_name": "decodeAttributeBody(byte[],char,char)", "file_path": "src/test/java/org/ice4j/attribute/AddressAttributeTest.java", "testclass_name": "AddressAttributeTest", "testcase_name": "testDecodeAttributeBodyv6"}, {"method_name": "encode()", "file_path": "src/test/java/org/ice4j/attribute/AddressAttributeTest.java", "testclass_name": "AddressAttributeTest", "testcase_name": "testEncode"}, {"method_name": "encode()", "file_path": "src/test/java/org/ice4j/attribute/AddressAttributeTest.java", "testclass_name": "AddressAttributeTest", "testcase_name": "testEncodev6"}, {"method_name": "equals(Object)", "file_path": "src/test/java/org/ice4j/attribute/AddressAttributeTest.java", "testclass_name": "AddressAttributeTest", "testcase_name": "testEquals"}, {"method_name": "getDataLength()", "file_path": "src/test/java/org/ice4j/attribute/AddressAttributeTest.java", "testclass_name": "AddressAttributeTest", "testcase_name": "testGetDataLength"}, {"method_name": "getName()", "file_path": "src/test/java/org/ice4j/attribute/AddressAttributeTest.java", "testclass_name": "AddressAttributeTest", "testcase_name": "testAddressAttributeDescendants"}, {"method_name": "getAttributeType()", "file_path": "src/test/java/org/ice4j/attribute/AddressAttributeTest.java", "testclass_name": "AddressAttributeTest", "testcase_name": "testAddressAttributeDescendants"}, {"method_name": "getFamily()", "file_path": "src/test/java/org/ice4j/attribute/AddressAttributeTest.java", "testclass_name": "AddressAttributeTest", "testcase_name": "testGetFamily"}], "UnknownAttributesAttribute": [{"method_name": "encode()", "file_path": "src/test/java/org/ice4j/attribute/UnknownAttributesAttributeTest.java", "testclass_name": "UnknownAttributesAttributeTest", "testcase_name": "testEncode"}, {"method_name": "equals(Object)", "file_path": "src/test/java/org/ice4j/attribute/UnknownAttributesAttributeTest.java", "testclass_name": "UnknownAttributesAttributeTest", "testcase_name": "testEquals"}, {"method_name": "getDataLength()", "file_path": "src/test/java/org/ice4j/attribute/UnknownAttributesAttributeTest.java", "testclass_name": "UnknownAttributesAttributeTest", "testcase_name": "testGetDataLength"}, {"method_name": "getName()", "file_path": "src/test/java/org/ice4j/attribute/UnknownAttributesAttributeTest.java", "testclass_name": "UnknownAttributesAttributeTest", "testcase_name": "testGetName"}, {"method_name": "getAttributeType()", "file_path": "src/test/java/org/ice4j/attribute/UnknownAttributesAttributeTest.java", "testclass_name": "UnknownAttributesAttributeTest", "testcase_name": "testUnknownAttributesAttribute"}, {"method_name": "getAttribute(int)", "file_path": "src/test/java/org/ice4j/attribute/UnknownAttributesAttributeTest.java", "testclass_name": "UnknownAttributesAttributeTest", "testcase_name": "testAddAttributeID"}, {"method_name": "getAttribute(int)", "file_path": "src/test/java/org/ice4j/attribute/UnknownAttributesAttributeTest.java", "testclass_name": "UnknownAttributesAttributeTest", "testcase_name": "testGetAttribute"}, {"method_name": "getAttributeCount()", "file_path": "src/test/java/org/ice4j/attribute/UnknownAttributesAttributeTest.java", "testclass_name": "UnknownAttributesAttributeTest", "testcase_name": "testAddAttributeID"}, {"method_name": "getAttributeCount()", "file_path": "src/test/java/org/ice4j/attribute/UnknownAttributesAttributeTest.java", "testclass_name": "UnknownAttributesAttributeTest", "testcase_name": "testDecodeAttributeBody"}, {"method_name": "getAttributeCount()", "file_path": "src/test/java/org/ice4j/attribute/UnknownAttributesAttributeTest.java", "testclass_name": "UnknownAttributesAttributeTest", "testcase_name": "testGetAttributeCount"}, {"method_name": "addAttributeID(char)", "file_path": "src/test/java/org/ice4j/attribute/UnknownAttributesAttributeTest.java", "testclass_name": "UnknownAttributesAttributeTest", "testcase_name": "testAddAttributeID"}, {"method_name": "addAttributeID(char)", "file_path": "src/test/java/org/ice4j/attribute/UnknownAttributesAttributeTest.java", "testclass_name": "UnknownAttributesAttributeTest", "testcase_name": "testEncode"}, {"method_name": "addAttributeID(char)", "file_path": "src/test/java/org/ice4j/attribute/UnknownAttributesAttributeTest.java", "testclass_name": "UnknownAttributesAttributeTest", "testcase_name": "testEquals"}, {"method_name": "addAttributeID(char)", "file_path": "src/test/java/org/ice4j/attribute/UnknownAttributesAttributeTest.java", "testclass_name": "UnknownAttributesAttributeTest", "testcase_name": "testGetAttribute"}, {"method_name": "addAttributeID(char)", "file_path": "src/test/java/org/ice4j/attribute/UnknownAttributesAttributeTest.java", "testclass_name": "UnknownAttributesAttributeTest", "testcase_name": "testGetAttributeCount"}, {"method_name": "addAttributeID(char)", "file_path": "src/test/java/org/ice4j/attribute/UnknownAttributesAttributeTest.java", "testclass_name": "UnknownAttributesAttributeTest", "testcase_name": "testGetAttributes"}, {"method_name": "addAttributeID(char)", "file_path": "src/test/java/org/ice4j/attribute/UnknownAttributesAttributeTest.java", "testclass_name": "UnknownAttributesAttributeTest", "testcase_name": "testGetDataLength"}, {"method_name": "decodeAttributeBody(byte[],int,char)", "file_path": "src/test/java/org/ice4j/attribute/UnknownAttributesAttributeTest.java", "testclass_name": "UnknownAttributesAttributeTest", "testcase_name": "testDecodeAttributeBody"}, {"method_name": "contains(char)", "file_path": "src/test/java/org/ice4j/attribute/UnknownAttributesAttributeTest.java", "testclass_name": "UnknownAttributesAttributeTest", "testcase_name": "testDecodeAttributeBody"}, {"method_name": "getAttributes()", "file_path": "src/test/java/org/ice4j/attribute/UnknownAttributesAttributeTest.java", "testclass_name": "UnknownAttributesAttributeTest", "testcase_name": "testGetAttributes"}], "Message": [{"method_name": "equals(Object)", "file_path": "src/test/java/org/ice4j/message/MessageTest.java", "testclass_name": "MessageTest", "testcase_name": "testEquals"}, {"method_name": "putAttribute(Attribute)", "file_path": "src/test/java/org/ice4j/message/MessageTest.java", "testclass_name": "MessageTest", "testcase_name": "testAddAndGetAttribute"}, {"method_name": "getAttribute(int)", "file_path": "src/test/java/org/ice4j/message/MessageTest.java", "testclass_name": "MessageTest", "testcase_name": "testAddAndGetAttribute"}, {"method_name": "encode(StunStack)", "file_path": "src/test/java/org/ice4j/message/MessageTest.java", "testclass_name": "MessageTest", "testcase_name": "testEncode"}, {"method_name": "decode(byte[],int,int)", "file_path": "src/test/java/org/ice4j/message/MessageTest.java", "testclass_name": "MessageTest", "testcase_name": "testDecode"}, {"method_name": "getAttributeCount()", "file_path": "src/test/java/org/ice4j/message/MessageTest.java", "testclass_name": "MessageTest", "testcase_name": "testGetAttributeCount"}, {"method_name": "removeAttribute(int)", "file_path": "src/test/java/org/ice4j/message/MessageTest.java", "testclass_name": "MessageTest", "testcase_name": "testRemoveAttribute"}], "PseudoTcpSocket": [{"method_name": "accept(int)", "file_path": "src/test/java/org/ice4j/pseudotcp/PseudoTcpStreamTest.java", "testclass_name": "PseudoTcpStreamTest", "testcase_name": "testConnectTransferClose"}, {"method_name": "connect(InetSocketAddress,int)", "file_path": "src/test/java/org/ice4j/pseudotcp/PseudoTcpStreamTest.java", "testclass_name": "PseudoTcpStreamTest", "testcase_name": "testConnectTransferClose"}, {"method_name": "read()", "file_path": "src/test/java/org/ice4j/pseudotcp/PseudoTcpStreamTest.java", "testclass_name": "PseudoTcpStreamTest", "testcase_name": "testConnectTransferClose"}, {"method_name": "write(byte[])", "file_path": "src/test/java/org/ice4j/pseudotcp/PseudoTcpStreamTest.java", "testclass_name": "PseudoTcpStreamTest", "testcase_name": "testConnectTransferClose"}, {"method_name": "close()", "file_path": "src/test/java/org/ice4j/pseudotcp/PseudoTcpStreamTest.java", "testclass_name": "PseudoTcpStreamTest", "testcase_name": "testConnectTransferClose"}], "PseudoTcpSocketImpl": [{"method_name": "accept(int)", "file_path": "src/test/java/org/ice4j/pseudotcp/PseudoTcpStreamTest.java", "testclass_name": "PseudoTcpStreamTest", "testcase_name": "testAccept"}, {"method_name": "write(byte[])", "file_path": "src/test/java/org/ice4j/pseudotcp/PseudoTcpStreamTest.java", "testclass_name": "PseudoTcpStreamTest", "testcase_name": "testWriteTimeout"}, {"method_name": "setPTCPOption(Option,int)", "file_path": "src/test/java/org/ice4j/pseudotcp/PseudoTcpStreamTest.java", "testclass_name": "PseudoTcpStreamTest", "testcase_name": "testReadTimeout"}, {"method_name": "setPTCPOption(Option,int)", "file_path": "src/test/java/org/ice4j/pseudotcp/PseudoTcpStreamTest.java", "testclass_name": "PseudoTcpStreamTest", "testcase_name": "testWriteTimeout"}, {"method_name": "setPTCPOption(Option,int)", "file_path": "src/test/java/org/ice4j/pseudotcp/PseudoTcpStreamTest.java", "testclass_name": "PseudoTcpStreamTest", "testcase_name": "testFlushTimeout"}, {"method_name": "read(byte[])", "file_path": "src/test/java/org/ice4j/pseudotcp/PseudoTcpStreamTest.java", "testclass_name": "PseudoTcpStreamTest", "testcase_name": "testReadTimeout"}, {"method_name": "flush()", "file_path": "src/test/java/org/ice4j/pseudotcp/PseudoTcpStreamTest.java", "testclass_name": "PseudoTcpStreamTest", "testcase_name": "testFlushTimeout"}], "PeriodicRunnable": [{"method_name": "schedule()", "file_path": "src/test/java/org/ice4j/util/PeriodicRunnableTests.java", "testclass_name": "PeriodicRunnableTests", "testcase_name": "scheduleExecutesSpecifiedRunnableMultipleTimes"}, {"method_name": "schedule()", "file_path": "src/test/java/org/ice4j/util/PeriodicRunnableTests.java", "testclass_name": "PeriodicRunnableTests", "testcase_name": "scheduleWithNegativeDelayDoesNotExecuteRunnable"}, {"method_name": "schedule()", "file_path": "src/test/java/org/ice4j/util/PeriodicRunnableTests.java", "testclass_name": "PeriodicRunnableTests", "testcase_name": "scheduleExecuteRunnableIfPreviouslyCancelled"}, {"method_name": "getDelayUntilNextRun()", "file_path": "src/test/java/org/ice4j/util/PeriodicRunnableTests.java", "testclass_name": "PeriodicRunnableTests", "testcase_name": "negativeDelayStopsFurtherExecution"}, {"method_name": "cancel()", "file_path": "src/test/java/org/ice4j/util/PeriodicRunnableTests.java", "testclass_name": "PeriodicRunnableTests", "testcase_name": "cancelStopFurtherExecution"}], "MessageFactory": [{"method_name": "createBindingErrorResponse(char)", "file_path": "src/test/java/org/ice4j/message/MessageFactoryTest.java", "testclass_name": "MessageFactoryTest", "testcase_name": "testCreateBindingErrorResponse"}, {"method_name": "createBindingErrorResponse(char,String)", "file_path": "src/test/java/org/ice4j/message/MessageFactoryTest.java", "testclass_name": "MessageFactoryTest", "testcase_name": "testCreateBindingErrorResponse1"}, {"method_name": "createBindingErrorResponseUnknownAttributes(char[])", "file_path": "src/test/java/org/ice4j/message/MessageFactoryTest.java", "testclass_name": "MessageFactoryTest", "testcase_name": "testCreateBindingErrorResponseUnknownAttributes"}, {"method_name": "createBindingErrorResponseUnknownAttributes(String,char[])", "file_path": "src/test/java/org/ice4j/message/MessageFactoryTest.java", "testclass_name": "MessageFactoryTest", "testcase_name": "testCreateBindingErrorResponseUnknownAttributes1"}, {"method_name": "createBindingRequest()", "file_path": "src/test/java/org/ice4j/message/MessageFactoryTest.java", "testclass_name": "MessageFactoryTest", "testcase_name": "testCreateBindingRequest"}, {"method_name": "create3489BindingResponse(TransportAddress,TransportAddress,TransportAddress)", "file_path": "src/test/java/org/ice4j/message/MessageFactoryTest.java", "testclass_name": "MessageFactoryTest", "testcase_name": "testCreateBindingResponse"}], "PseudoTcpTestRecvWindow": [{"method_name": "getShadowedBytes(int)", "file_path": "src/test/java/org/ice4j/pseudotcp/PseudoTcpTestRecvWindow.java", "testclass_name": "PseudoTcpTestRecvWindow", "testcase_name": "testGetShadowedBytes"}, {"method_name": "doTestTransfer(int)", "file_path": "src/test/java/org/ice4j/pseudotcp/PseudoTcpTestRecvWindow.java", "testclass_name": "PseudoTcpTestRecvWindow", "testcase_name": "testReceiveWindow"}, {"method_name": "doTestTransfer(int)", "file_path": "src/test/java/org/ice4j/pseudotcp/PseudoTcpTestRecvWindow.java", "testclass_name": "PseudoTcpTestRecvWindow", "testcase_name": "testSetVerySmallSendWindowSize"}, {"method_name": "doTestTransfer(int)", "file_path": "src/test/java/org/ice4j/pseudotcp/PseudoTcpTestRecvWindow.java", "testclass_name": "PseudoTcpTestRecvWindow", "testcase_name": "testSetReceiveWindowSize"}], "AttributeDecoder": [{"method_name": "decode(byte[],char,char)", "file_path": "src/test/java/org/ice4j/attribute/AttributeDecoderTest.java", "testclass_name": "AttributeDecoderTest", "testcase_name": "testDecodeMappedAddress"}, {"method_name": "decode(byte[],char,char)", "file_path": "src/test/java/org/ice4j/attribute/AttributeDecoderTest.java", "testclass_name": "AttributeDecoderTest", "testcase_name": "testDecodeMappedAddress_v6"}, {"method_name": "decode(byte[],char,char)", "file_path": "src/test/java/org/ice4j/attribute/AttributeDecoderTest.java", "testclass_name": "AttributeDecoderTest", "testcase_name": "testDecodeChangeRequest"}, {"method_name": "decode(byte[],char,char)", "file_path": "src/test/java/org/ice4j/attribute/AttributeDecoderTest.java", "testclass_name": "AttributeDecoderTest", "testcase_name": "testDecodeErrorCode"}, {"method_name": "decode(byte[],char,char)", "file_path": "src/test/java/org/ice4j/attribute/AttributeDecoderTest.java", "testclass_name": "AttributeDecoderTest", "testcase_name": "testDecodeUnknownAttributes"}, {"method_name": "decode(byte[],char,char)", "file_path": "src/test/java/org/ice4j/attribute/AttributeDecoderTest.java", "testclass_name": "AttributeDecoderTest", "testcase_name": "testDecodeUnknownOptionalAttribute"}], "StunStack": [{"method_name": "sendRequest(Request,TransportAddress,TransportAddress,AbstractResponseCollector)", "file_path": "src/test/java/org/ice4j/MessageEventDispatchingTest.java", "testclass_name": "MessageEventDispatchingTest", "testcase_name": "testClientTransactionTimeouts"}, {"method_name": "sendRequest(Request,TransportAddress,TransportAddress,AbstractResponseCollector)", "file_path": "src/test/java/org/ice4j/MessageEventDispatchingTest.java", "testclass_name": "MessageEventDispatchingTest", "testcase_name": "testEventDispatchingUponIncomingRequests"}, {"method_name": "sendRequest(Request,TransportAddress,TransportAddress,AbstractResponseCollector)", "file_path": "src/test/java/org/ice4j/MessageEventDispatchingTest.java", "testclass_name": "MessageEventDispatchingTest", "testcase_name": "testSelectiveEventDispatchingUponIncomingRequests"}, {"method_name": "sendRequest(Request,TransportAddress,TransportAddress,AbstractResponseCollector)", "file_path": "src/test/java/org/ice4j/MessageEventDispatchingTest.java", "testclass_name": "MessageEventDispatchingTest", "testcase_name": "testServerResponseRetransmissions"}, {"method_name": "sendResponse(byte[],Response,TransportAddress,TransportAddress)", "file_path": "src/test/java/org/ice4j/MessageEventDispatchingTest.java", "testclass_name": "MessageEventDispatchingTest", "testcase_name": "testServerResponseRetransmissions"}, {"method_name": "sendResponse(byte[],Response,TransportAddress,TransportAddress)", "file_path": "src/test/java/org/ice4j/stack/ShallowStackTest.java", "testclass_name": "ShallowStackTest", "testcase_name": "testSendResponse"}, {"method_name": "sendResponse(byte[],Response,TransportAddress,TransportAddress)", "file_path": "src/test/java/org/ice4j/TransactionSupportTests.java", "testclass_name": "TransactionSupportTests", "testcase_name": "testServerResponseRetransmissions"}, {"method_name": "sendResponse(byte[],Response,TransportAddress,TransportAddress)", "file_path": "src/test/java/org/ice4j/TransactionSupportTests.java", "testclass_name": "TransactionSupportTests", "testcase_name": "testUniqueIDs"}, {"method_name": "sendRequest(Request,TransportAddress,TransportAddress,ResponseCollector)", "file_path": "src/test/java/org/ice4j/stack/ShallowStackTest.java", "testclass_name": "ShallowStackTest", "testcase_name": "testSendRequest"}, {"method_name": "sendRequest(Request,TransportAddress,TransportAddress,ResponseCollector)", "file_path": "src/test/java/org/ice4j/stack/ShallowStackTest.java", "testclass_name": "ShallowStackTest", "testcase_name": "testReceiveResponse"}, {"method_name": "sendRequest(Request,TransportAddress,TransportAddress,ResponseCollector)", "file_path": "src/test/java/org/ice4j/stack/ShallowStackTest.java", "testclass_name": "ShallowStackTest", "testcase_name": "testRetransmissionOriginalWait"}, {"method_name": "sendRequest(Request,TransportAddress,TransportAddress,ResponseCollector)", "file_path": "src/test/java/org/ice4j/TransactionSupportTests.java", "testclass_name": "TransactionSupportTests", "testcase_name": "testClientRetransmissions"}, {"method_name": "sendRequest(Request,TransportAddress,TransportAddress,ResponseCollector)", "file_path": "src/test/java/org/ice4j/TransactionSupportTests.java", "testclass_name": "TransactionSupportTests", "testcase_name": "testServerRetransmissionHiding"}, {"method_name": "sendRequest(Request,TransportAddress,TransportAddress,ResponseCollector)", "file_path": "src/test/java/org/ice4j/TransactionSupportTests.java", "testclass_name": "TransactionSupportTests", "testcase_name": "testServerResponseRetransmissions"}, {"method_name": "sendRequest(Request,TransportAddress,TransportAddress,ResponseCollector)", "file_path": "src/test/java/org/ice4j/TransactionSupportTests.java", "testclass_name": "TransactionSupportTests", "testcase_name": "testUniqueIDs"}, {"method_name": "sendRequest(Request,TransportAddress,TransportAddress,ResponseCollector)", "file_path": "src/test/java/org/ice4j/TransactionSupportTests.java", "testclass_name": "TransactionSupportTests", "testcase_name": "testClientTransactionMaxRetransmisssionsConfigurationParameter"}, {"method_name": "sendRequest(Request,TransportAddress,TransportAddress,ResponseCollector)", "file_path": "src/test/java/org/ice4j/TransactionSupportTests.java", "testclass_name": "TransactionSupportTests", "testcase_name": "testMinWaitIntervalConfigurationParameter"}, {"method_name": "sendRequest(Request,TransportAddress,TransportAddress,ResponseCollector)", "file_path": "src/test/java/org/ice4j/TransactionSupportTests.java", "testclass_name": "TransactionSupportTests", "testcase_name": "testMaxWaitIntervalConfigurationParameter"}, {"method_name": "addRequestListener(RequestListener)", "file_path": "src/test/java/org/ice4j/stack/ShallowStackTest.java", "testclass_name": "ShallowStackTest", "testcase_name": "testReceiveRequest"}], "NetworkConfigurationDiscoveryProcess": [{"method_name": "determineAddress()", "file_path": "src/test/java/org/ice4j/stunclient/StunAddressDiscovererTest_v4v6.java", "testclass_name": "StunAddressDiscovererTest_v4v6", "testcase_name": "testRecognizeSymmetricNat_Local_v6_Public_v4"}, {"method_name": "determineAddress()", "file_path": "src/test/java/org/ice4j/stunclient/StunAddressDiscovererTest_v4v6.java", "testclass_name": "StunAddressDiscovererTest_v4v6", "testcase_name": "testRecognizeSymmetricNat_Local_v4_Public_v6"}, {"method_name": "determineAddress()", "file_path": "src/test/java/org/ice4j/stunclient/StunAddressDiscovererTest_v4v6.java", "testclass_name": "StunAddressDiscovererTest_v4v6", "testcase_name": "testRecognizeFullCone_Local_v6_Public_v4"}, {"method_name": "determineAddress()", "file_path": "src/test/java/org/ice4j/stunclient/StunAddressDiscovererTest_v4v6.java", "testclass_name": "StunAddressDiscovererTest_v4v6", "testcase_name": "testRecognizeFullCone_Local_v4_Public_v6"}, {"method_name": "determineAddress()", "file_path": "src/test/java/org/ice4j/stunclient/StunAddressDiscovererTest_v6.java", "testclass_name": "StunAddressDiscovererTest_v6", "testcase_name": "testRecognizeBlockedUDP"}, {"method_name": "determineAddress()", "file_path": "src/test/java/org/ice4j/stunclient/StunAddressDiscovererTest_v6.java", "testclass_name": "StunAddressDiscovererTest_v6", "testcase_name": "testRecognizeSymmetricNat"}, {"method_name": "determineAddress()", "file_path": "src/test/java/org/ice4j/stunclient/StunAddressDiscovererTest_v6.java", "testclass_name": "StunAddressDiscovererTest_v6", "testcase_name": "testRecognizePortRestrictedCone"}, {"method_name": "determineAddress()", "file_path": "src/test/java/org/ice4j/stunclient/StunAddressDiscovererTest_v6.java", "testclass_name": "StunAddressDiscovererTest_v6", "testcase_name": "testRecognizeRestrictedCone"}, {"method_name": "determineAddress()", "file_path": "src/test/java/org/ice4j/stunclient/StunAddressDiscovererTest_v6.java", "testclass_name": "StunAddressDiscovererTest_v6", "testcase_name": "testRecognizeFullCone"}, {"method_name": "determineAddress()", "file_path": "src/test/java/org/ice4j/stunclient/StunAddressDiscovererTest_v6.java", "testclass_name": "StunAddressDiscovererTest_v6", "testcase_name": "testRecognizeUdpSymmetricFirewall"}, {"method_name": "determineAddress()", "file_path": "src/test/java/org/ice4j/stunclient/StunAddressDiscovererTest_v6.java", "testclass_name": "StunAddressDiscovererTest_v6", "testcase_name": "testRecognizeOpenInternet"}, {"method_name": "determineAddress()", "file_path": "src/test/java/org/ice4j/stunclient/StunAddressDiscovererTest.java", "testclass_name": "StunAddressDiscovererTest", "testcase_name": "testRecognizeBlockedUDP"}, {"method_name": "determineAddress()", "file_path": "src/test/java/org/ice4j/stunclient/StunAddressDiscovererTest.java", "testclass_name": "StunAddressDiscovererTest", "testcase_name": "testRecognizeSymmetricNat"}, {"method_name": "determineAddress()", "file_path": "src/test/java/org/ice4j/stunclient/StunAddressDiscovererTest.java", "testclass_name": "StunAddressDiscovererTest", "testcase_name": "testRecognizePortRestrictedCone"}, {"method_name": "determineAddress()", "file_path": "src/test/java/org/ice4j/stunclient/StunAddressDiscovererTest.java", "testclass_name": "StunAddressDiscovererTest", "testcase_name": "testRecognizeRestrictedCone"}, {"method_name": "determineAddress()", "file_path": "src/test/java/org/ice4j/stunclient/StunAddressDiscovererTest.java", "testclass_name": "StunAddressDiscovererTest", "testcase_name": "testRecognizeFullCone"}, {"method_name": "determineAddress()", "file_path": "src/test/java/org/ice4j/stunclient/StunAddressDiscovererTest.java", "testclass_name": "StunAddressDiscovererTest", "testcase_name": "testRecognizeUdpSymmetricFirewall"}, {"method_name": "determineAddress()", "file_path": "src/test/java/org/ice4j/stunclient/StunAddressDiscovererTest.java", "testclass_name": "StunAddressDiscovererTest", "testcase_name": "testRecognizeOpenInternet"}], "XorMappedAddressAttribute": [{"method_name": "applyXor(byte[])", "file_path": "src/test/java/org/ice4j/attribute/AddressAttributeTest.java", "testclass_name": "AddressAttributeTest", "testcase_name": "testXorMappedAddressXoring_v4"}, {"method_name": "applyXor(byte[])", "file_path": "src/test/java/org/ice4j/attribute/AddressAttributeTest.java", "testclass_name": "AddressAttributeTest", "testcase_name": "testXorMappedAddressXoring_v6"}], "ByteFifoBuffer": [{"method_name": "length()", "file_path": "src/test/java/org/ice4j/pseudotcp/util/ByteFifoBufferTest.java", "testclass_name": "ByteFifoBufferTest", "testcase_name": "testLength"}, {"method_name": "read(byte[],int)", "file_path": "src/test/java/org/ice4j/pseudotcp/util/ByteFifoBufferTest.java", "testclass_name": "ByteFifoBufferTest", "testcase_name": "testRead"}, {"method_name": "read(byte[],int,int)", "file_path": "src/test/java/org/ice4j/pseudotcp/util/ByteFifoBufferTest.java", "testclass_name": "ByteFifoBufferTest", "testcase_name": "testReadWithOffset"}, {"method_name": "getWriteRemaining()", "file_path": "src/test/java/org/ice4j/pseudotcp/util/ByteFifoBufferTest.java", "testclass_name": "ByteFifoBufferTest", "testcase_name": "testGetWriteRemaining"}, {"method_name": "getWriteRemaining()", "file_path": "src/test/java/org/ice4j/pseudotcp/util/ByteFifoBufferTest.java", "testclass_name": "ByteFifoBufferTest", "testcase_name": "testWriteReadWriteRead"}, {"method_name": "getBuffered()", "file_path": "src/test/java/org/ice4j/pseudotcp/util/ByteFifoBufferTest.java", "testclass_name": "ByteFifoBufferTest", "testcase_name": "testGetBuffered"}, {"method_name": "getBuffered()", "file_path": "src/test/java/org/ice4j/pseudotcp/util/ByteFifoBufferTest.java", "testclass_name": "ByteFifoBufferTest", "testcase_name": "testWriteReadWriteRead"}, {"method_name": "write(byte[],int)", "file_path": "src/test/java/org/ice4j/pseudotcp/util/ByteFifoBufferTest.java", "testclass_name": "ByteFifoBufferTest", "testcase_name": "testWrite"}, {"method_name": "write(byte[],int,int)", "file_path": "src/test/java/org/ice4j/pseudotcp/util/ByteFifoBufferTest.java", "testclass_name": "ByteFifoBufferTest", "testcase_name": "testWriteWithOffset"}, {"method_name": "consumeWriteBuffer(int)", "file_path": "src/test/java/org/ice4j/pseudotcp/util/ByteFifoBufferTest.java", "testclass_name": "ByteFifoBufferTest", "testcase_name": "testConsumeWriteBuffer"}, {"method_name": "consumeWriteBuffer(int)", "file_path": "src/test/java/org/ice4j/pseudotcp/util/ByteFifoBufferTest.java", "testclass_name": "ByteFifoBufferTest", "testcase_name": "testWriteReadWriteRead"}, {"method_name": "consumeWriteBuffer(int)", "file_path": "src/test/java/org/ice4j/pseudotcp/util/ByteFifoBufferTest.java", "testclass_name": "ByteFifoBufferTest", "testcase_name": "testSomeMultiTest"}, {"method_name": "setCapacity(int)", "file_path": "src/test/java/org/ice4j/pseudotcp/util/ByteFifoBufferTest.java", "testclass_name": "ByteFifoBufferTest", "testcase_name": "testSetCapacity"}, {"method_name": "consumeReadData(int)", "file_path": "src/test/java/org/ice4j/pseudotcp/util/ByteFifoBufferTest.java", "testclass_name": "ByteFifoBufferTest", "testcase_name": "testConsumeReadData"}, {"method_name": "consumeReadData(int)", "file_path": "src/test/java/org/ice4j/pseudotcp/util/ByteFifoBufferTest.java", "testclass_name": "ByteFifoBufferTest", "testcase_name": "testWriteReadWriteRead"}, {"method_name": "readOffset(byte[],int,int,int)", "file_path": "src/test/java/org/ice4j/pseudotcp/util/ByteFifoBufferTest.java", "testclass_name": "ByteFifoBufferTest", "testcase_name": "testReadOffset"}, {"method_name": "readOffset(byte[],int,int,int)", "file_path": "src/test/java/org/ice4j/pseudotcp/util/ByteFifoBufferTest.java", "testclass_name": "ByteFifoBufferTest", "testcase_name": "testWriteReadWriteRead"}, {"method_name": "readOffset(byte[],int,int,int)", "file_path": "src/test/java/org/ice4j/pseudotcp/util/ByteFifoBufferTest.java", "testclass_name": "ByteFifoBufferTest", "testcase_name": "testSomeMultiTest"}, {"method_name": "writeOffset(byte[],int,int)", "file_path": "src/test/java/org/ice4j/pseudotcp/util/ByteFifoBufferTest.java", "testclass_name": "ByteFifoBufferTest", "testcase_name": "testWriteOffset"}, {"method_name": "writeOffset(byte[],int,int)", "file_path": "src/test/java/org/ice4j/pseudotcp/util/ByteFifoBufferTest.java", "testclass_name": "ByteFifoBufferTest", "testcase_name": "testWriteReadWriteRead"}, {"method_name": "writeOffset(byte[],int,int)", "file_path": "src/test/java/org/ice4j/pseudotcp/util/ByteFifoBufferTest.java", "testclass_name": "ByteFifoBufferTest", "testcase_name": "testSomeMultiTest"}], "PseudoTCPBase": [{"method_name": "doTestPingPong(int,int)", "file_path": "src/test/java/org/ice4j/pseudotcp/PseudoTcpTestPingPong.java", "testclass_name": "PseudoTcpTestPingPong", "testcase_name": "testPingPong1xMtu"}, {"method_name": "doTestPingPong(int,int)", "file_path": "src/test/java/org/ice4j/pseudotcp/PseudoTcpTestPingPong.java", "testclass_name": "PseudoTcpTestPingPong", "testcase_name": "testPingPong3xMtu"}, {"method_name": "doTestPingPong(int,int)", "file_path": "src/test/java/org/ice4j/pseudotcp/PseudoTcpTestPingPong.java", "testclass_name": "PseudoTcpTestPingPong", "testcase_name": "testPingPong2xMtu"}, {"method_name": "doTestPingPong(int,int)", "file_path": "src/test/java/org/ice4j/pseudotcp/PseudoTcpTestPingPong.java", "testclass_name": "PseudoTcpTestPingPong", "testcase_name": "testPingPong2xMtuWithAckDelayOff"}, {"method_name": "doTestPingPong(int,int)", "file_path": "src/test/java/org/ice4j/pseudotcp/PseudoTcpTestPingPong.java", "testclass_name": "PseudoTcpTestPingPong", "testcase_name": "testPingPong2xMtuWithNaglingOff"}, {"method_name": "doTestPingPong(int,int)", "file_path": "src/test/java/org/ice4j/pseudotcp/PseudoTcpTestPingPong.java", "testclass_name": "PseudoTcpTestPingPong", "testcase_name": "testPingPongShortSegments"}, {"method_name": "doTestPingPong(int,int)", "file_path": "src/test/java/org/ice4j/pseudotcp/PseudoTcpTestPingPong.java", "testclass_name": "PseudoTcpTestPingPong", "testcase_name": "testPingPongShortSegmentsWithNaglingOff"}, {"method_name": "doTestPingPong(int,int)", "file_path": "src/test/java/org/ice4j/pseudotcp/PseudoTcpTestPingPong.java", "testclass_name": "PseudoTcpTestPingPong", "testcase_name": "testPingPongShortSegmentsWithAckDelayOff"}]}