{"target_method": "describeTo", "signature": "StringBuilder describeTo(StringBuilder)", "gwt_enhancements": {"Given": {"enhanced_by": [{"method_name": "toString()", "relation_type": "State Change Similarity", "confidence": 0.9, "reason": "Both methods involve constructing a string representation of the Pos object.", "is_external": false}, {"method_name": "sum(Iterable<Pos>)", "relation_type": "Dependency Similarity", "confidence": 0.75, "reason": "Both methods manipulate Pos objects, and sum() can be used to create a complex Pos object for testing describeTo().", "is_external": false}]}, "Then": {"enhanced_by": [{"method_name": "equals(Object)", "relation_type": "Output Comparison", "confidence": 0.85, "reason": "The describeTo() method's output can be compared to the expected string representation generated by the equals() method.", "is_external": false}, {"method_name": "plus(Pos)", "relation_type": "Behavior Similarity", "confidence": 0.8, "reason": "Both methods involve manipulating Pos objects, and the output of describeTo() can be validated against the expected result from plus().", "is_external": false}]}}}