{"target_method": "toString", "signature": "String toString()", "direct_enhancements": [{"method_name": "clone()", "relation_type": "Structural Similarity", "confidence": 0.85, "reason": "Both methods involve creating a representation of the object, one for string and one for cloning.", "is_external": false}, {"method_name": "getName()", "relation_type": "Behavioral Similarity", "confidence": 0.9, "reason": "Both methods return a string representation, one of the entire object and one of a specific attribute.", "is_external": false}, {"method_name": "getValue()", "relation_type": "Behavioral Similarity", "confidence": 0.9, "reason": "Both methods return a string representation, one of the entire object and one of a specific attribute.", "is_external": false}, {"method_name": "getJsType()", "relation_type": "Behavioral Similarity", "confidence": 0.9, "reason": "Both methods return a string representation, one of the entire object and one of a specific attribute.", "is_external": false}, {"method_name": "isResource()", "relation_type": "Behavioral Similarity", "confidence": 0.85, "reason": "Both methods return a representation, one of the entire object and one of a specific attribute.", "is_external": false}], "gwt_enhancements": {"Given": {"enhanced_by": [{"method_name": "setName(String)", "relation_type": "State Change Similarity", "confidence": 0.8, "reason": "Setting the name is required to test the toString method.", "is_external": false}, {"method_name": "setValue(String)", "relation_type": "State Change Similarity", "confidence": 0.8, "reason": "Setting the value is required to test the toString method.", "is_external": false}, {"method_name": "setJsType(String)", "relation_type": "State Change Similarity", "confidence": 0.8, "reason": "Setting the JavaScript type is required to test the toString method.", "is_external": false}, {"method_name": "setResource(boolean)", "relation_type": "State Change Similarity", "confidence": 0.8, "reason": "Setting the resource flag is required to test the toString method.", "is_external": false}]}, "When": {"enhanced_by": [{"method_name": "toString()", "relation_type": "Self-Invocation", "confidence": 1.0, "reason": "The toString method itself is the method to be invoked.", "is_external": false}]}, "Then": {"enhanced_by": [{"method_name": "getName()", "relation_type": "Behavioral Similarity", "confidence": 0.9, "reason": "The name returned by getName can be used to verify the toString output.", "is_external": false}, {"method_name": "getValue()", "relation_type": "Behavioral Similarity", "confidence": 0.9, "reason": "The value returned by getValue can be used to verify the toString output.", "is_external": false}, {"method_name": "getJsType()", "relation_type": "Behavioral Similarity", "confidence": 0.9, "reason": "The JavaScript type returned by getJsType can be used to verify the toString output.", "is_external": false}, {"method_name": "isResource()", "relation_type": "Behavioral Similarity", "confidence": 0.85, "reason": "The resource flag returned by isResource can be used to verify the toString output.", "is_external": false}]}}}