{"target_method": "fillInStackTrace", "signature": "Throwable fillInStackTrace()", "gwt_enhancements": {"When": {"enhanced_by": [{"method_name": "super.fillInStackTrace()", "relation_type": "State Dependency", "confidence": 0.95, "reason": "The superclass method must be invoked to capture the initial stack trace before filtering.", "is_external": false}]}, "Then": {"enhanced_by": [{"method_name": "setStackTrace(StackTraceElement[])", "relation_type": "State Mutation Similarity", "confidence": 0.9, "reason": "Both methods manipulate the stack trace, making assertions about the final state of the stack trace relevant.", "is_external": false}]}}}