{"target_method": "getIterator", "signature": "Iterator<?> getIterator(Object)", "gwt_enhancements": {"Given": {"enhanced_by": [{"method_name": "arrayIterator(Object)", "relation_type": "Input Pattern Similarity", "confidence": 0.9, "reason": "Both methods handle array-like objects and return iterators.", "is_external": false}, {"method_name": "asIterator(Enumeration)", "relation_type": "Input Pattern Similarity", "confidence": 0.8, "reason": "Both methods convert different types of input (Enumeration and Object) to iterators.", "is_external": false}, {"method_name": "singletonIterator(Object)", "relation_type": "Input Pattern Similarity", "confidence": 0.7, "reason": "Both methods handle single objects and return iterators.", "is_external": false}]}, "When": {"enhanced_by": [{"method_name": "asIterable(Iterator)", "relation_type": "State Dependency", "confidence": 0.8, "reason": "The asIterable method can be used to convert the iterator returned by getIterator to an Iterable, which might be necessary for certain operations.", "is_external": false}, {"method_name": "toArray(Iterator)", "relation_type": "State Dependency", "confidence": 0.7, "reason": "The toArray method can be used to convert the iterator returned by getIterator to an array, which might be necessary for certain operations.", "is_external": false}]}}}