{"target_method": "putAll", "signature": "void putAll(Map<? extends K, ? extends V>)", "gwt_enhancements": {"Given": {"enhanced_by": [{"method_name": "put(K,V)", "relation_type": "State Change Similarity", "confidence": 0.9, "reason": "putAll internally uses put to add each entry from the specified map, making it a direct precursor for setting up the map state.", "is_external": false}, {"method_name": "clear()", "relation_type": "State Reset Similarity", "confidence": 0.7, "reason": "Clearing the map before invoking putAll can help in setting up a clean state for testing the method.", "is_external": false}]}, "When": {"enhanced_by": [{"method_name": "atomic(Runnable)", "relation_type": "Execution Order Dependency", "confidence": 0.8, "reason": "Wrapping putAll inside atomic ensures that the operation is executed atomically, which can be crucial for thread-safe testing scenarios.", "is_external": false}, {"method_name": "size()", "relation_type": "State Verification", "confidence": 0.7, "reason": "Invoking size after putAll can help verify the correct number of entries added to the map.", "is_external": false}]}}}