{"target_method": "notifyClock", "signature": "void notifyClock(long)", "gwt_enhancements": {"Given": {"enhanced_by": [{"method_name": "connect()", "relation_type": "State Initialization", "confidence": 0.9, "reason": "The connect method initializes the state to TCP_LISTEN, which is a prerequisite for notifyClock to function correctly.", "is_external": false}, {"method_name": "notifyMTU(int)", "relation_type": "Resource Configuration", "confidence": 0.8, "reason": "The notifyMTU method sets the MTU value, which is used in the notifyClock method to adjust the retransmission timer.", "is_external": false}]}, "When": {"enhanced_by": [{"method_name": "attemptSend(SendFlags)", "relation_type": "State Dependency", "confidence": 0.85, "reason": "The attemptSend method is invoked within notifyClock to handle the sending of packets, ensuring that the state is updated and packets are transmitted as needed.", "is_external": false}, {"method_name": "closedown(IOException)", "relation_type": "Error Handling", "confidence": 0.75, "reason": "The closedown method is called within notifyClock to handle errors and close the connection if necessary.", "is_external": false}]}}}