{"target_method": "onTcpOpen", "signature": "void onTcpOpen(PseudoTCPBase)", "gwt_enhancements": {"Given": {"enhanced_by": [{"method_name": "startThreads()", "relation_type": "State Change Similarity", "confidence": 0.9, "reason": "Both methods involve setting up threads and initializing the socket state.", "is_external": false}, {"method_name": "doConnect(InetSocketAddress,long)", "relation_type": "State Change Similarity", "confidence": 0.8, "reason": "The doConnect method sets up the connection and prepares the socket for the onTcpOpen event.", "is_external": false}]}, "When": {"enhanced_by": [{"method_name": "onTcpWriteable(PseudoTCPBase)", "relation_type": "State Dependency", "confidence": 0.7, "reason": "onTcpOpen is often followed by onTcpWriteable to indicate that the socket is ready for writing.", "is_external": false}, {"method_name": "onTcpReadable(PseudoTCPBase)", "relation_type": "State Dependency", "confidence": 0.7, "reason": "onTcpOpen is often followed by onTcpReadable to indicate that the socket is ready for reading.", "is_external": false}]}}}