{"target_method": "removeIgnoreCase", "signature": "void removeIgnoreCase(String)", "gwt_enhancements": {"Given": {"enhanced_by": [{"method_name": "putIgnoreCase(String,String)", "relation_type": "State Change Similarity", "confidence": 0.9, "reason": "Both methods involve operations on attributes with case-insensitive keys.", "is_external": false}, {"method_name": "hasKeyIgnoreCase(String)", "relation_type": "Input Validation Similarity", "confidence": 0.85, "reason": "Both methods require checking for the presence of an attribute by case-insensitive key.", "is_external": false}]}, "Then": {"enhanced_by": [{"method_name": "hasKeyIgnoreCase(String)", "relation_type": "Output Validation Similarity", "confidence": 0.9, "reason": "The presence of the key after removal can be verified using hasKeyIgnoreCase.", "is_external": false}, {"method_name": "size()", "relation_type": "State Verification", "confidence": 0.8, "reason": "The size of the Attributes object can be checked before and after removal to verify the removal operation.", "is_external": false}]}}}