{"target_method": "escapeCssIdentifier", "signature": "String escapeCssIdentifier(String)", "gwt_enhancements": {"Given": {"enhanced_by": [{"method_name": "consumeCssIdentifier()", "relation_type": "Input Pattern Similarity", "confidence": 0.9, "reason": "Both methods process CSS identifiers and handle similar character patterns.", "is_external": false}, {"method_name": "consumeElementSelector()", "relation_type": "Input Pattern Similarity", "confidence": 0.85, "reason": "Both methods process CSS selectors and handle similar character patterns.", "is_external": false}]}, "Then": {"enhanced_by": [{"method_name": "unescape(String)", "relation_type": "Output Transformation Similarity", "confidence": 0.9, "reason": "Both methods involve escaping and unescaping characters, which can inform the construction of assertions for the output.", "is_external": false}, {"method_name": "consumeEscapedCssIdentifier(String...)", "relation_type": "Output Transformation Similarity", "confidence": 0.85, "reason": "Both methods involve processing escaped CSS identifiers, which can inform the construction of assertions for the output.", "is_external": false}]}}}