{"target_method": "digit", "signature": "int digit(int)", "gwt_enhancements": {"Given": {"enhanced_by": [{"method_name": "calculateWeight(String,int,int,int)", "relation_type": "Input Dependency", "confidence": 0.9, "reason": "The digit method relies on the output of the calculateWeight method to compute the verifying digit.", "is_external": false}]}, "Then": {"enhanced_by": [{"method_name": "isCNPJValid(String)", "relation_type": "Output Verification", "confidence": 0.85, "reason": "The digit method's output is used in the validation logic of the isCNPJValid method to verify the CNPJ.", "is_external": false}, {"method_name": "isCPFValid(String)", "relation_type": "Output Verification", "confidence": 0.85, "reason": "The digit method's output is used in the validation logic of the isCPFValid method to verify the CPF.", "is_external": false}]}}}