{"target_method": "pop", "signature": "ImmutableStack<T> pop()", "gwt_enhancements": {"Given": {"enhanced_by": [{"method_name": "push(T)", "relation_type": "State Change Similarity", "confidence": 0.9, "reason": "Both methods manipulate the stack by either adding or removing elements.", "is_external": false}, {"method_name": "create(T)", "relation_type": "Object Initialization", "confidence": 0.85, "reason": "The create method initializes a stack, which can be used to set up a non-empty stack for pop testing.", "is_external": false}]}, "Then": {"enhanced_by": [{"method_name": "isEmpty()", "relation_type": "State Verification", "confidence": 0.9, "reason": "The isEmpty method can be used to verify the state of the stack after a pop operation.", "is_external": false}, {"method_name": "peek()", "relation_type": "Behavior Similarity", "confidence": 0.85, "reason": "Both methods interact with the stack's head element, making peek useful for verifying post-pop state.", "is_external": false}]}}}